mltracker/__init__.py
mltracker/adapters/experiments.py
mltracker/adapters/iterations.py
mltracker/adapters/metrics.py
mltracker/adapters/models.py
mltracker/adapters/modules.py
mltracker/adapters/steps.py
mltracker/getters.py
mltracker/ports/__init__.py
mltracker/ports/experiments.py
mltracker/ports/iterations.py
mltracker/ports/metrics.py
mltracker/ports/models.py
mltracker/ports/modules.py
mltracker-0.4.0.dist-info/METADATA
mltracker-0.4.0.dist-info/WHEEL
mltracker-0.4.0.dist-info/licenses/LICENSE
mltracker-0.4.0.dist-info/RECORD
