Metadata-Version: 2.4
Name: mltracker
Version: 0.4.0
Summary: Track machine learning experiments.
License: MIT
License-File: LICENSE
Author: entropy-flux
Author-email: eric.hermosis@gmail.com
Requires-Python: >=3.12, <4.0
Classifier: License :: OSI Approved :: MIT License
Classifier: Programming Language :: Python :: 3
Classifier: Programming Language :: Python :: 3.12
Classifier: Programming Language :: Python :: 3.13
Classifier: Programming Language :: Python :: 3.14
